octocheck.py
octocheck-0.0.4.dist-info/METADATA
octocheck-0.0.4.dist-info/WHEEL
octocheck-0.0.4.dist-info/entry_points.txt
octocheck-0.0.4.dist-info/top_level.txt
octocheck-0.0.4.dist-info/RECORD
