Metadata-Version: 2.1
Name: octocheck
Version: 0.0.4
Summary: A reporter utility for Github Checks
Home-page: https://github.com/sigmaris/octocheck
Author: Hugh Cole-Baker
Author-email: sigmaris@gmail.com
License: UNKNOWN
Platform: UNKNOWN
Classifier: Programming Language :: Python :: 3
Classifier: Programming Language :: Python :: 3.6
Classifier: Programming Language :: Python :: 3.7
Requires-Dist: github3.py (~=1.3.0)
